{
    "file_name":"D:\\pdf\\pdf\\d0265161d0ed290ff81ff99e4571de9b709b357c9e663ad2b4519b68497705f5",
    "\/JS":0,
    "\/AA":0,
    "\/OpenAction":0,
    "\/AcroForm":0,
    "\/RichMedia":0,
    "\/Launch":0,
    "\/EmbeddedFile":0,
    "\/XFA":0,
    "\/URI":1,
    "\/F":0,
    "\/GoToE":0,
    "\/Extends":0,
    "\/Annot":1,
    "\/Length":1,
    "\/Filter":26,
    "\/FlateDecode":23,
    "\/XObject":5,
    "\/Encrypt":0,
    "\/CreationDate":2,
    "\/Author":1,
    "subject":1,
    "\/ModDate":1,
    "html":1,
    "Script":2,
    "powershell.exe":0,
    "cmd.exe":0,
    "#[0-9]([0-9|A-z])":0,
    "sys":15,
    "root":0,
    "reg":0,
    "exe":1,
    "http":3,
    "domain":0,
    "filepath":28,
    "ascii":30,
    "xml":2,
    "dll":0,
    "unescape":0,
    "%u9090%u9090":0,
    "getIcon":0,
    "temp,tmp":0,
    "eval":0,
    "%appdata%":0,
    "chunk":0,
    "base64":0,
    "mkdir":0,
    "replace":0,
    "fromCharCode":0,
    "getAnnots":0,
    "ip":3,
    "xref_size":74,
    "trailer_size":74,
    "file_size":121.81,
    "nof_stream":65,
    "cve":0,
    "yara":0
}